sa/__init__.py
sa/_version.py
sa/docker_api.py
sa/repo.py
sa/source_assist.py
sa/utils.py
sa/versioning.py
Source_Assist-0.3.4.dist-info/LICENSE
Source_Assist-0.3.4.dist-info/METADATA
Source_Assist-0.3.4.dist-info/WHEEL
Source_Assist-0.3.4.dist-info/entry_points.txt
Source_Assist-0.3.4.dist-info/top_level.txt
Source_Assist-0.3.4.dist-info/RECORD
