Metadata-Version: 2.1
Name: Source-Assist
Version: 0.3.4
Summary: A DevOps automation tool for incrementing version numbers and git repo management
Home-page: https://github.com/projectinitiative/SourceAssist
Author: Kyle Petryszak
Author-email: 
License: UNKNOWN
Project-URL: Bug Tracker, https://github.com/projectinitiative/SourceAssist/issues
Platform: UNKNOWN
Classifier: Programming Language :: Python :: 3
Classifier: Operating System :: OS Independent
Requires-Python: >=3.6
Requires-Dist: docker
Requires-Dist: gitpython
